obsidian_workflow/__init__.py
obsidian_workflow/__main__.py
obsidian_workflow/cli.py
obsidian_workflow/daily.py
plugins/python scripter/process daily note/src/main.py
tests/test_daily.py
tests/test_obsidian_workflow.py
obsidian_workflow-0.0.3.dist-info/METADATA
obsidian_workflow-0.0.3.dist-info/WHEEL
obsidian_workflow-0.0.3.dist-info/entry_points.txt
obsidian_workflow-0.0.3.dist-info/top_level.txt
obsidian_workflow-0.0.3.dist-info/RECORD
