Metadata-Version: 2.1
Name: obsidian-workflow
Version: 0.0.3
Summary: Obsidian workflow tools for automating my obsidian workflow
Author: Brandt Beal
License: MIT License
Project-URL: Homepage, https://github.com/babeal/obsidian-workflow
Project-URL: Changelog, https://github.com/babeal/obsidian-workflow/releases
Project-URL: Issues, https://github.com/babeal/obsidian-workflow/issues
Project-URL: CI, https://github.com/babeal/obsidian-workflow/actions
Classifier: License :: OSI Approved :: MIT License
Requires-Python: >=3.10
Requires-Dist: click
